{
  "students": [
  {
    "studentName": "Soniya",
    "category": "indian",
    "documents": [
      {
        "name": "Domicile Certificate",
        "selected": true,
        "required": "true"
      },
      {
        "name": "Birth Certificate",
        "selected": true,
        "required": "true"
      },
      {
        "name": "Previous marksheets",
        "selected": true,
        "required": "true"
      },
      {
        "name": "Police clearance",
        "selected": false,
        "required": "false"
      },
      {
        "name": "Passport",
        "selected": false,
        "required": "false"
      },
      {
        "name": "Signed declaration",
        "selected": true,
        "required": "true"
      }
    ],
    "dob": "2019-04-01T18:30:00.000Z",
    "fatherName": "Devender",
    "motherName": "Lalita",
    "lastClassScore": "87",
    "id": 1
  },
  {
    "studentName": "David",
    "category": "international",
    "documents": [
      {
        "name": "Domicile Certificate",
        "selected": true,
        "required": "true"
      },
      {
        "name": "Birth Certificate",
        "selected": true,
        "required": "true"
      },
      {
        "name": "Previous marksheets",
        "selected": true,
        "required": "true"
      },
      {
        "name": "Police clearance",
        "selected": true,
        "required": "true"
      },
      {
        "name": "Passport",
        "selected": true,
        "required": "true"
      },
      {
        "name": "Signed declaration",
        "selected": true,
        "required": "true"
      }
    ],
    "dob": "2019-04-01T18:30:00.000Z",
    "fatherName": "Daniel",
    "motherName": "Rose",
    "lastClassScore": "89",
    "id": 2
  },
  {
    "studentName": "Lily",
    "category": "international",
    "documents": [
      {
        "name": "Domicile Certificate",
        "selected": true,
        "required": "true"
      },
      {
        "name": "Birth Certificate",
        "selected": true,
        "required": "true"
      },
      {
        "name": "Previous marksheets",
        "selected": true,
        "required": "true"
      },
      {
        "name": "Police clearance",
        "selected": true,
        "required": "true"
      },
      {
        "name": "Passport",
        "selected": true,
        "required": "true"
      },
      {
        "name": "Signed declaration",
        "selected": true,
        "required": "true"
      }
    ],
    "dob": "2019-04-02T18:30:00.000Z",
    "fatherName": "Joe",
    "motherName": "Josie",
    "lastClassScore": "80",
    "id": 3
  },
  {
    "studentName": "Lizie",
    "category": "international",
    "documents": [
      {
        "name": "Domicile Certificate",
        "selected": true,
        "required": "true"
      },
      {
        "name": "Birth Certificate",
        "selected": true,
        "required": "true"
      },
      {
        "name": "Previous marksheets",
        "selected": true,
        "required": "true"
      },
      {
        "name": "Police clearance",
        "selected": true,
        "required": "true"
      },
      {
        "name": "Passport",
        "selected": true,
        "required": "true"
      },
      {
        "name": "Signed declaration",
        "selected": true,
        "required": "true"
      }
    ],
    "dob": "2019-04-02T18:30:00.000Z",
    "fatherName": "Alaric",
    "motherName": "Josset",
    "lastClassScore": "85",
    "id": 4
  },
  {
    "studentName": "Karan",
    "category": "indian",
    "documents": [
      {
        "name": "Domicile Certificate",
        "selected": true,
        "required": "true"
      },
      {
        "name": "Birth Certificate",
        "selected": true,
        "required": "true"
      },
      {
        "name": "Previous marksheets",
        "selected": true,
        "required": "true"
      },
      {
        "name": "Police clearance",
        "selected": false,
        "required": "false"
      },
      {
        "name": "Passport",
        "selected": false,
        "required": "false"
      },
      {
        "name": "Signed declaration",
        "selected": true,
        "required": "true"
      }
    ],
    "dob": "2019-04-03T18:30:00.000Z",
    "fatherName": "Viren",
    "motherName": "Kriti",
    "lastClassScore": "90",
    "id": 5
  }
],
  "users": [
    {
      "email": "admin@nag.com",
      "username": "admin",
      "password": "adminpassword",
      "id": 1
    },
    {
      "email": "adminuser@nag.com",
      "username": "admin user",
      "password": "adminuserpassword",
      "id": 2
    },
    {
      "email": "user@nag.com",
      "username": "user",
      "password": "userpass",
      "id": 3
    }
  ],
  "indianDocs": [
    {
      "name": "Domicile Certificate",
      "required": "true"
    },
    {
      "name": "Birth Certificate",
      "required": "true"
    },
    {
      "name": "Previous marksheets",
      "required": "true"
    },
    {
      "name": "Police clearance",
      "required": "false"
    },
    {
      "name": "Passport",
      "required": "false"
    },
    {
      "name": "Signed declaration",
      "required": "true"
    }
  ],
  "internationalDocs": [
    {
      "name": "Domicile Certificate",
      "required": "true"
    },
    {
      "name": "Birth Certificate",
      "required": "true"
    },
    {
      "name": "Previous marksheets",
      "required": "true"
    },
    {
      "name": "Police clearance",
      "required": "true"
    },
    {
      "name": "Passport",
      "required": "true"
    },
    {
      "name": "Signed declaration",
      "required": "true"
    }
  ]
}
